{
    "name": "IClientGameNotificationsMap",
    "functions": [ 
        {
            "name": "EnumerateNotifications",
            "argc": "2",
            "interfaceid": "37",
            "functionid": "1374609452",
            "fencepost": "1463372038",
            "cannotcallincrossprocess": "0",
            "serializedargs": [
                "bytes4"
            ],
            "serializedreturns": [
                "bytes8"
            ]
        },
        {
            "name": "GetNotificationCount",
            "argc": "2",
            "interfaceid": "37",
            "functionid": "2971932933",
            "fencepost": "3060711648",
            "cannotcallincrossprocess": "0",
            "serializedargs": [
                "bytes4"
            ],
            "serializedreturns": [
                "bytes4"
            ]
        },
        {
            "name": "GetNotification",
            "argc": "4",
            "interfaceid": "37",
            "functionid": "2154781907",
            "fencepost": "2243641267",
            "cannotcallincrossprocess": "0",
            "serializedargs": [
                "bytes4",
                "bytes4"
            ],
            "serializedreturns": [
                "bytes1",
                "bytes4124"
            ]
        },
        {
            "name": "RemoveSession",
            "argc": "4",
            "interfaceid": "37",
            "functionid": "1416988664",
            "fencepost": "1505896411",
            "cannotcallincrossprocess": "0",
            "serializedargs": [
                "bytes4",
                "bytes8"
            ],
            "serializedreturns": [
            ]
        },
        {
            "name": "UpdateSession",
            "argc": "4",
            "interfaceid": "37",
            "functionid": "138145638",
            "fencepost": "227069514",
            "cannotcallincrossprocess": "0",
            "serializedargs": [
                "bytes4",
                "bytes8"
            ],
            "serializedreturns": [
            ]
        }
    ]
}
