{
    "name": "IClientVRMap",
    "functions": [ 
        {
            "name": "GetCurrentHmd",
            "argc": "1",
            "interfaceid": "40",
            "functionid": "3314327953",
            "fencepost": "3405139303",
            "cannotcallincrossprocess": "1",
            "serializedargs": [
            ],
            "serializedreturns": [
                "bytes4"
            ]
        },
        {
            "name": "GetCompositor",
            "argc": "1",
            "interfaceid": "40",
            "functionid": "3044474249",
            "fencepost": "3135301728",
            "cannotcallincrossprocess": "1",
            "serializedargs": [
            ],
            "serializedreturns": [
                "bytes4"
            ]
        },
        {
            "name": "GetOverlay",
            "argc": "1",
            "interfaceid": "40",
            "functionid": "3792889322",
            "fencepost": "3883732930",
            "cannotcallincrossprocess": "1",
            "serializedargs": [
            ],
            "serializedreturns": [
                "bytes4"
            ]
        },
        {
            "name": "GetSettings",
            "argc": "1",
            "interfaceid": "40",
            "functionid": "4117870175",
            "fencepost": "4208729912",
            "cannotcallincrossprocess": "1",
            "serializedargs": [
            ],
            "serializedreturns": [
                "bytes4"
            ]
        },
        {
            "name": "GetProperties",
            "argc": "1",
            "interfaceid": "40",
            "functionid": "1343220579",
            "fencepost": "1434096445",
            "cannotcallincrossprocess": "1",
            "serializedargs": [
            ],
            "serializedreturns": [
                "bytes4"
            ]
        },
        {
            "name": "GetPaths",
            "argc": "1",
            "interfaceid": "40",
            "functionid": "2947276079",
            "fencepost": "3038168074",
            "cannotcallincrossprocess": "1",
            "serializedargs": [
            ],
            "serializedreturns": [
                "bytes4"
            ]
        },
        {
            "name": "IsHmdPresent",
            "argc": "1",
            "interfaceid": "40",
            "functionid": "2488295319",
            "fencepost": "2579203443",
            "cannotcallincrossprocess": "0",
            "serializedargs": [
            ],
            "serializedreturns": [
                "boolean"
            ]
        },
        {
            "name": "UpdateHmdStatus",
            "argc": "1",
            "interfaceid": "40",
            "functionid": "150169886",
            "fencepost": "241094139",
            "cannotcallincrossprocess": "0",
            "serializedargs": [
            ],
            "serializedreturns": [
            ]
        },
        {
            "name": "IsVRModeActive",
            "argc": "1",
            "interfaceid": "40",
            "functionid": "1755772078",
            "fencepost": "1846712460",
            "cannotcallincrossprocess": "0",
            "serializedargs": [
            ],
            "serializedreturns": [
                "boolean"
            ]
        },
        {
            "name": "InitVR",
            "argc": "4",
            "interfaceid": "40",
            "functionid": "3006200455",
            "fencepost": "3097221482",
            "cannotcallincrossprocess": "0",
            "serializedargs": [
                "bytes1"
            ],
            "serializedreturns": [
                "bytes1",
                "bytes4",
                "bytes4"
            ]
        },
        {
            "name": "StartSteamVR",
            "argc": "2",
            "interfaceid": "40",
            "functionid": "63095665",
            "fencepost": "154181208",
            "cannotcallincrossprocess": "0",
            "serializedargs": [
                "string"
            ],
            "serializedreturns": [
                "bytes1"
            ]
        },
        {
            "name": "CleanupVR",
            "argc": "1",
            "interfaceid": "40",
            "functionid": "1294880811",
            "fencepost": "1385982483",
            "cannotcallincrossprocess": "0",
            "serializedargs": [
            ],
            "serializedreturns": [
            ]
        },
        {
            "name": "QuitAllVR",
            "argc": "1",
            "interfaceid": "40",
            "functionid": "3315847112",
            "fencepost": "3406964913",
            "cannotcallincrossprocess": "0",
            "serializedargs": [
            ],
            "serializedreturns": [
            ]
        },
        {
            "name": "QuitApplication",
            "argc": "2",
            "interfaceid": "40",
            "functionid": "1631735490",
            "fencepost": "1722869420",
            "cannotcallincrossprocess": "0",
            "serializedargs": [
                "bytes4"
            ],
            "serializedreturns": [
            ]
        },
        {
            "name": "GetStringForHmdError",
            "argc": "2",
            "interfaceid": "40",
            "functionid": "45218545",
            "fencepost": "136368604",
            "cannotcallincrossprocess": "0",
            "serializedargs": [
                "bytes4"
            ],
            "serializedreturns": [
                "string"
            ]
        },
        {
            "name": "LaunchApplication",
            "argc": "2",
            "interfaceid": "40",
            "functionid": "2921129905",
            "fencepost": "3012296093",
            "cannotcallincrossprocess": "0",
            "serializedargs": [
                "string"
            ],
            "serializedreturns": [
                "bytes1"
            ]
        },
        {
            "name": "GetSteamVRAppId",
            "argc": "1",
            "interfaceid": "40",
            "functionid": "772581627",
            "fencepost": "863763944",
            "cannotcallincrossprocess": "0",
            "serializedargs": [
            ],
            "serializedreturns": [
                "bytes4"
            ]
        },
        {
            "name": "GetSteamVRPid",
            "argc": "1",
            "interfaceid": "40",
            "functionid": "4212766423",
            "fencepost": "8997573",
            "cannotcallincrossprocess": "0",
            "serializedargs": [
            ],
            "serializedreturns": [
                "bytes4"
            ]
        },
        {
            "name": "GetWebSecret",
            "argc": "1",
            "interfaceid": "40",
            "functionid": "1497598032",
            "fencepost": "1588812607",
            "cannotcallincrossprocess": "0",
            "serializedargs": [
            ],
            "serializedreturns": [
                "bytes8"
            ]
        },
        {
            "name": "BGetMutualCapabilities",
            "argc": "2",
            "interfaceid": "40",
            "functionid": "3809641887",
            "fencepost": "3900904849",
            "cannotcallincrossprocess": "0",
            "serializedargs": [
            ],
            "serializedreturns": [
                "boolean",
                "unknown"
            ]
        },
        {
            "name": "BSteamCanMakeVROverlays",
            "argc": "1",
            "interfaceid": "40",
            "functionid": "319465985",
            "fencepost": "410777334",
            "cannotcallincrossprocess": "0",
            "serializedargs": [
            ],
            "serializedreturns": [
                "boolean"
            ]
        },
        {
            "name": "BServeVRGamepadUIOverlay",
            "argc": "1",
            "interfaceid": "40",
            "functionid": "3953200051",
            "fencepost": "4044527529",
            "cannotcallincrossprocess": "0",
            "serializedargs": [
            ],
            "serializedreturns": [
                "boolean"
            ]
        },
        {
            "name": "BServeVRGamepadUIViaGamescope",
            "argc": "1",
            "interfaceid": "40",
            "functionid": "815765670",
            "fencepost": "907109277",
            "cannotcallincrossprocess": "0",
            "serializedargs": [
            ],
            "serializedreturns": [
                "boolean"
            ]
        },
        {
            "name": "SetVRConnectionParams",
            "argc": "2",
            "interfaceid": "40",
            "functionid": "94557412",
            "fencepost": "185917148",
            "cannotcallincrossprocess": "0",
            "serializedargs": [
                "string"
            ],
            "serializedreturns": [
            ]
        },
        {
            "name": "GetVRConnectionParams",
            "argc": "1",
            "interfaceid": "40",
            "functionid": "4019831287",
            "fencepost": "4111207152",
            "cannotcallincrossprocess": "0",
            "serializedargs": [
            ],
            "serializedreturns": [
                "string"
            ]
        },
        {
            "name": "BVRDeviceSeenRecently",
            "argc": "1",
            "interfaceid": "40",
            "functionid": "3564968914",
            "fencepost": "3656360908",
            "cannotcallincrossprocess": "0",
            "serializedargs": [
            ],
            "serializedreturns": [
                "boolean"
            ]
        }
    ]
}
