{
    "name": "IClientCompatMap",
    "found_at": "0x23759b8",
    "functions": [ 
        {
            "name": "BIsCompatLayerEnabled",
            "argc": "1",
            "addr": "0x609550"
        },
        {
            "name": "EnableCompat",
            "argc": "2",
            "addr": "0x6096b0"
        },
        {
            "name": "GetAvailableCompatTools",
            "argc": "2",
            "addr": "0x609800"
        },
        {
            "name": "GetAvailableCompatToolsFiltered",
            "argc": "3",
            "addr": "0x609970"
        },
        {
            "name": "GetAvailableCompatToolsForApp",
            "argc": "3",
            "addr": "0x609af0"
        },
        {
            "name": "SpecifyCompatTool",
            "argc": "5",
            "addr": "0x609c70"
        },
        {
            "name": "BIsCompatibilityToolEnabled",
            "argc": "2",
            "addr": "0x609de0"
        },
        {
            "name": "GetCompatToolName",
            "argc": "2",
            "addr": "0x609f60"
        },
        {
            "name": "GetCompatToolMappingPriority",
            "argc": "2",
            "addr": "0x60a0d0"
        },
        {
            "name": "GetCompatToolDisplayName",
            "argc": "2",
            "addr": "0x60a240"
        },
        {
            "name": "GetWhitelistedGameList",
            "argc": "2",
            "addr": "0x60ac90"
        },
        {
            "name": "GetControllerConfigOverrides",
            "argc": "2",
            "addr": "0x60ae00"
        },
        {
            "name": "StartSession",
            "argc": "2",
            "addr": "0x60a3b0"
        },
        {
            "name": "ReleaseSession",
            "argc": "4",
            "addr": "0x60a540"
        },
        {
            "name": "BIsLauncherServiceEnabled",
            "argc": "2",
            "addr": "0x60a6b0"
        },
        {
            "name": "DeleteCompatData",
            "argc": "2",
            "addr": "0x60a830"
        },
        {
            "name": "GetCompatibilityDataDiskSize",
            "argc": "2",
            "addr": "0x60a980"
        },
        {
            "name": "BNeedsUnlockH264",
            "argc": "2",
            "addr": "0x60ab10"
        }
    ]
}
